{
  "basics": {
    "name": "روكو روسو",
    "label": "مهندس برمجيات واجهة أمامية",
    "image": "/assets/png/profile.png",
    "email": "rocco.russo.dev@gmail.com",
    "phone": "+34 604 06 87 00",
    "url": "https://xdemocle.eu",
    "summary": "مهندس برمجيات واجهة أمامية بخبرة تزيد عن 8 سنوات في تطوير الويب. أقوم ببناء تطبيقات ويب عالية الأداء وسهلة الوصول باستخدام React و TypeScript وأطر العمل الحديثة.",
    "location": {
      "address": "",
      "postalCode": "",
      "city": "مالقة",
      "countryCode": "ES",
      "region": "أندلوسيا"
    },
    "profiles": [
      {
        "network": "GitHub",
        "username": "xdemocle",
        "url": "https://github.com/xdemocle"
      },
      {
        "network": "LinkedIn",
        "username": "roccorusso",
        "url": "https://linkedin.com/in/roccorusso"
      },
      {
        "network": "Twitter",
        "username": "xdemocle",
        "url": "https://twitter.com/xdemocle"
      }
    ]
  },
  "work": [
    {
      "name": "The Web3 Ninja",
      "position": "مهندس برمجيات واجهة أمامية",
      "url": "https://theweb3.ninja",
      "startDate": "2024-09-01",
      "endDate": "",
      "summary": "بناء حلول web3 مع التركيز على أداء الواجهة الأمامية وتجربة المستخدم لتطبيقات البلوكشين.",
      "highlights": [
        "تحسين مكونات React لعرض بيانات البلوكشين، مما قلل من أوقات التحميل بنسبة 40%"
      ],
      "location": "عن بُعد"
    }
  ],
  "volunteer": [],
  "education": [
    {
      "institution": "مدرسة أثينا",
      "url": "",
      "area": "علوم الحاسوب",
      "studyType": "دورة مهنية",
      "startDate": "2009-01-01",
      "endDate": "2010-01-01",
      "score": "",
      "courses": []
    }
  ],
  "awards": [
    {
      "title": "أفضل 10% في Stack Overflow",
      "date": "2019-01-01",
      "awarder": "Stack Overflow",
      "summary": "مصنف باستمرار ضمن أفضل 10% من المساهمين لعلامات React و JavaScript."
    }
  ],
  "certificates": [
    {
      "name": "React - الدليل الشامل (يشمل Hooks، React Router، Redux)",
      "date": "2020-01-01",
      "issuer": "Udemy - Academind بواسطة Maximilian Schwarzmüller",
      "url": "https://www.udemy.com/certificate/UC-1Y9Z2R3N/"
    }
  ],
  "publications": [],
  "skills": [
    {
      "name": "الواجهة الأمامية",
      "level": "خبير",
      "keywords": [
        "React",
        "React Router",
        "Preact",
        "Svelte",
        "TypeScript",
        "JavaScript",
        "Next.js",
        "Remix",
        "Redux"
      ]
    }
  ],
  "languages": [
    {
      "language": "الإنجليزية",
      "fluency": "كفاءة مهنية"
    },
    {
      "language": "الإسبانية",
      "fluency": "كفاءة أساسية"
    },
    {
      "language": "الإيطالية",
      "fluency": "كفاءة أصلية أو ثنائية اللغة"
    }
  ],
  "interests": [
    {
      "name": "التكنولوجيا",
      "keywords": [
        "تطوير الويب",
        "البلوكشين",
        "AI/ML",
        "إنترنت الأشياء",
        "الأمن السيبراني"
      ]
    },
    {
      "name": "الهوايات",
      "keywords": [
        "التصوير الفوتوغرافي",
        "السفر",
        "الألعاب",
        "الطبخ",
        "القراءة"
      ]
    }
  ],
  "references": [],
  "projects": [
    {
      "name": "Ajna Labs - تطبيق DeFi + SDK",
      "description": "تصميم تطبيق مالي لامركزي و SDK للإقراض والاقتراض في فضاء web3. تم بناؤه باستخدام React و TypeScript و Ethers.js وعقود Solidity الذكية.",
      "highlights": [
        "مدمج مع أكثر من 5 شبكات بلوكشين للإقراض عبر السلاسل",
        "مصممة واجهة عالية الأداء تدير أكثر من مليون دولار في المعاملات",
        "تم تطوير SDK مستخدم من قبل أكثر من 10 مطورين خارجيين للتكاملات المخصصة"
      ],
      "keywords": [
        "React",
        "TypeScript",
        "Ethers.js",
        "Solidity",
        "DeFi",
        "Web3"
      ],
      "startDate": "2022-01-01",
      "endDate": "2022-12-01",
      "url": "https://ajna.finance",
      "roles": ["قائد الواجهة الأمامية"],
      "entity": "Ajna Labs",
      "type": "application"
    },
    {
      "name": "Mode Network - إعادة هيكلة React على نطاق واسع",
      "description": "قيادة إعادة هيكلة تطبيق React أحادي إلى قاعدة كود معيارية وقابلة للصيانة لشبكة بلوكشين من الطبقة الثانية.",
      "highlights": [
        "تقليل الدين الفني بنسبة 60% من خلال تجزئة المكونات",
        "تحسين أوقات تحميل الصفحات بنسبة 35% مع تقسيم الكود والتحميل الكسول",
        "إرشاد فريق من 4 مطورين حول أنماط React الحديثة"
      ],
      "keywords": ["React", "TypeScript", "تحسين الأداء", "إعادة هيكلة الكود"],
      "startDate": "2023-01-01",
      "endDate": "2023-12-01",
      "url": "https://mode.network",
      "roles": ["قائد الواجهة الأمامية"],
      "entity": "Mode Network",
      "type": "application"
    },
    {
      "name": "GamesGlobal - ماكينات القمار ذات الجائزة الكبرى التقدمية Lotsaloot™",
      "description": "تطوير ألعاب ماكينات القمار ذات الجائزة الكبرى التقدمية مع ميزات متعددة اللاعبين في الوقت الحقيقي ورسومات عالية الأداء.",
      "highlights": [
        "بناء نظام ماكينات قمار متعددة اللاعبين يدير أكثر من 1000 مستخدم متزامن",
        "تحسين عرض WebGL للحصول على 60 إطارًا في الثانية على الأجهزة منخفضة الجودة",
        "دمج بوابات دفع آمنة للمعاملات اليومية التي تزيد عن 100,000 دولار"
      ],
      "keywords": ["React", "WebGL", "WebSocket", "الألعاب", "متعدد اللاعبين"],
      "startDate": "2022-01-01",
      "endDate": "2024-01-01",
      "url": "https://gamesglobal.com",
      "roles": ["مهندس الواجهة الأمامية"],
      "entity": "Games Global",
      "type": "application"
    },
    {
      "name": "Landworks by EnterDAO - نظام تأجير الميتافيرس",
      "description": "تطوير نظام تأجير لامركزي للأراضي الافتراضية في الميتافيرس، مدمج مع ملكية NFT والعقود الذكية.",
      "highlights": [
        "بناء سوق تأجير NFT مع أكثر من 500 مستخدم نشط شهريًا",
        "دمج العقود الذكية للتأجير والدفعات الآلية",
        "تحسين واجهة المستخدم لمعاينات الأصول ثلاثية الأبعاد المعقدة باستخدام Three.js"
      ],
      "keywords": ["React", "TypeScript", "Three.js", "NFT", "Web3", "DeFi"],
      "startDate": "2021-01-01",
      "endDate": "2022-01-01",
      "url": "https://enterdao.xyz",
      "roles": ["مطور الواجهة الأمامية"],
      "entity": "EnterDAO",
      "type": "application"
    },
    {
      "name": "Omnia DeFi - لوحة تحكم Dapp للأصول في العالم الحقيقي",
      "description": "بناء لوحة تحكم للتمويل اللامركزي لإدارة الأصول الحقيقية المميزة مع بيانات وتحليلات في الوقت الحقيقي.",
      "highlights": [
        "تطوير لوحة تحكم لتتبع الأصول لأكثر من 2 مليون دولار في الأصول المميزة",
        "دمج بيانات البلوكشين في الوقت الحقيقي مع بروتوكول The Graph",
        "تصميم واجهة مستخدم متجاوبة للمستثمرين على سطح المكتب والجوال"
      ],
      "keywords": ["React", "GraphQL", "The Graph", "DeFi", "Web3"],
      "startDate": "2021-01-01",
      "endDate": "2022-01-01",
      "url": "https://omnia-defi.com",
      "roles": ["مطور الواجهة الأمامية"],
      "entity": "Omnia DeFi",
      "type": "application"
    },
    {
      "name": "Lokr.io (سابقًا Polkalokr) - موقع تسويقي",
      "description": "تصميم وتطوير موقع تسويقي لمنصة قفل الرموز المستندة إلى البلوكشين مع محتوى ديناميكي.",
      "highlights": [
        "بناء موقع مدفوع بنظام إدارة المحتوى مع أكثر من 10,000 زائر شهريًا",
        "تحسين لتحسين محركات البحث، محققًا المرتبة الثلاثة الأولى للمصطلحات الرئيسية",
        "دمج مصادقة محفظة web3 لميزات العرض التوضيحي"
      ],
      "keywords": ["React", "Next.js", "SEO", "مصادقة Web3"],
      "startDate": "2021-01-01",
      "endDate": "2021-12-01",
      "url": "https://lokr.io",
      "roles": ["مطور الواجهة الأمامية"],
      "entity": "Lokr.io",
      "type": "website"
    },
    {
      "name": "AltCash - مبادل العملات الرقمية B2C",
      "description": "تطوير منصة لتبادل العملات الرقمية للمعاملات B2C مع معالجة الدفعات مدمجة.",
      "highlights": [
        "بناء واجهة تبادل تدير أكثر من 50,000 دولار في تبادلات العملات الرقمية اليومية",
        "دمج أكثر من 5 بوابات دفع لتحويل العملات الورقية إلى العملات الرقمية",
        "تصميم مصادقة مستخدم آمنة مع التحقق من KYC"
      ],
      "keywords": ["React", "Node.js", "بوابة الدفع", "العملات الرقمية"],
      "startDate": "2020-01-01",
      "endDate": "2021-01-01",
      "url": "https://alt.cash",
      "roles": ["مطور Full Stack"],
      "entity": "AltCash",
      "type": "application"
    },
    {
      "name": "CyberGrandpa مكافحة الاحتيال - امتداد المتصفح",
      "description": "إنشاء امتداد متصفح للكشف عن الاحتيال عبر الإنترنت ومنعه للمستخدمين الضعفاء مع تنبيهات في الوقت الحقيقي.",
      "highlights": [
        "تطوير امتداد مع أكثر من 1000 مستخدم نشط على متجر Chrome",
        "تنفيذ كشف الاحتيال المستند إلى التعلم الآلي بدقة 85%",
        "تصميم واجهة مستخدم بديهية للمستخدمين المسنين غير التقنيين"
      ],
      "keywords": ["JavaScript", "امتداد المتصفح", "التعلم الآلي", "UX"],
      "startDate": "2019-01-01",
      "endDate": "2020-01-01",
      "url": "https://github.com/xdemocle/cybergrandpa",
      "roles": ["المطور الرئيسي"],
      "entity": "مشروع شخصي",
      "type": "application"
    },
    {
      "name": "LinkedIn Full Width - امتداد تحسين واجهة المستخدم",
      "description": "بناء امتداد متصفح لتحسين واجهة مستخدم LinkedIn عن طريق تعظيم عرض المحتوى وإزالة المشتتات.",
      "highlights": [
        "تحقيق أكثر من 500 تنزيل بتقييم 4.8/5",
        "زيادة إنتاجية المستخدم من خلال تحسين تخطيط المحتوى",
        "الحفاظ على التوافق عبر تحديثات واجهة LinkedIn"
      ],
      "keywords": [
        "JavaScript",
        "CSS",
        "امتداد المتصفح",
        "تحسين واجهة المستخدم"
      ],
      "startDate": "2018-01-01",
      "endDate": "2019-01-01",
      "url": "https://github.com/xdemocle/linkedin-full-width",
      "roles": ["المنشئ"],
      "entity": "مشروع شخصي",
      "type": "application"
    },
    {
      "name": "Tetris مع مكافآت العملات الرقمية - تطبيق صغير على Telegram",
      "description": "تطوير لعبة Tetris كتطبيق صغير على Telegram مع مكافآت عملات رقمية مدمجة لجذب اللاعبين.",
      "highlights": [
        "بناء لعبة مع أكثر من 2000 لاعب نشط في الشهر الأول",
        "دمج محفظة بلوكشين لمكافآت صغيرة بالـ ETH",
        "تحسين الأداء للحصول على لعب سلس على الجوال"
      ],
      "keywords": ["React", "تطوير الألعاب", "API Telegram", "Web3"],
      "startDate": "2023-01-01",
      "endDate": "2023-12-01",
      "url": "https://t.me/tetris_crypto_bot",
      "roles": ["المطور الرئيسي"],
      "entity": "مشروع شخصي",
      "type": "application"
    }
  ]
}
